winpwn/__init__.py
winpwn/context.py
winpwn/dbg.py
winpwn/misc.py
winpwn/var.py
winpwn/win.py
winpwn/winpwn.py
macpwn-0.0.1.dist-info/METADATA
macpwn-0.0.1.dist-info/WHEEL
macpwn-0.0.1.dist-info/top_level.txt
macpwn-0.0.1.dist-info/RECORD
